[{"category": ["Chinese"], "geoLocation": [40.4758737, -74.2823519], "neighborhood": [], "name": ["Hunan House"], "starRating": [], "phone": ["(732) 727-0420"], "priceRange": [], "address": ["327 S Pine Ave", "South Amboy, NJ 08879"], "numberOfReviews": []},
{"category": ["Delis"], "geoLocation": [40.4825244, -74.2835682], "neighborhood": [], "name": ["South Amboy Deli & Subs"], "starRating": ["3.0 star rating"], "phone": ["(732) 727-6202"], "priceRange": ["$"], "address": ["101 N Stevens Ave", "South Amboy, NJ 08879"], "numberOfReviews": ["5 reviews"]},
{"category": ["Delis", "Sandwiches"], "geoLocation": [40.4643786, -74.2625764], "neighborhood": [], "name": ["Kaili Fashionista Emporium"], "starRating": [], "phone": ["(732) 721-0100"], "priceRange": [], "address": ["1836 State Route 35", "South Amboy, NJ 08879"], "numberOfReviews": []},
{"category": ["Pizza"], "geoLocation": [40.4658534, -74.2750179], "neighborhood": [], "name": ["Mama Mias Pizza"], "starRating": [], "phone": ["(732) 401-0831"], "priceRange": [], "address": ["337 S Pine Ave", "South Amboy, NJ 08879"], "numberOfReviews": []},
{"category": ["Pizza"], "geoLocation": [40.4844303, -74.2856064], "neighborhood": [], "name": ["Don Giovanni NY Style Pizza"], "starRating": [], "phone": ["(732) 727-0733"], "priceRange": [], "address": ["276 Main St", "South Amboy, NJ 08879"], "numberOfReviews": []},
{"category": ["Delis"], "geoLocation": [40.4842365, -74.2883378], "neighborhood": [], "name": ["Center Deli"], "starRating": [], "phone": ["(732) 721-9082"], "priceRange": [], "address": ["250 N Stevens Ave", "South Amboy, NJ 08879"], "numberOfReviews": []},
{"category": ["Delis"], "geoLocation": [40.4871324, -74.2945945], "neighborhood": [], "name": ["New Deluxe Deli"], "starRating": [], "phone": ["(732) 525-1850"], "priceRange": [], "address": ["528 Ridgeway Ave", "South Amboy, NJ 08879"], "numberOfReviews": []},
{"category": ["Restaurants"], "geoLocation": [40.4778838, -74.290702], "neighborhood": [], "name": ["Host Marriott Travel Plaza"], "starRating": [], "phone": ["(732) 525-0306"], "priceRange": [], "address": ["Garden State Pkwy", "South Amboy, NJ 08879"], "numberOfReviews": []},
{"category": ["Pizza"], "geoLocation": [40.4778838, -74.290702], "neighborhood": [], "name": ["Lisa"], "starRating": [], "phone": ["(732) 290-1313"], "priceRange": [], "address": ["RR 35", "South Amboy, NJ 08879"], "numberOfReviews": []},
{"category": ["Hot Dogs"], "geoLocation": [40.484308, -74.28014], "neighborhood": [], "name": ["Nathan\u2019s Famous"], "starRating": ["2.0 star rating"], "phone": ["(732) 525-0306"], "priceRange": ["$$"], "address": ["Garden State Pkwy", "South Amboy, NJ 08879"], "numberOfReviews": ["1 review"]},
{"category": ["Seafood"], "geoLocation": [40.4643862, -74.2626466], "neighborhood": [], "name": ["Covelos"], "starRating": [], "phone": ["(732) 727-6388"], "priceRange": [], "address": ["1792 Route 35 N", "South Amboy, NJ 08879"], "numberOfReviews": []},
{"category": ["Portuguese"], "geoLocation": [40.4648738524837, -74.2642487124752], "neighborhood": [], "name": ["Fernandes 3"], "starRating": [], "phone": ["(732) 721-2306"], "priceRange": [], "address": ["189 Morgan Ave", "South Amboy, NJ 08879"], "numberOfReviews": []},
{"category": ["Seafood", "Steakhouses"], "geoLocation": [40.4756700363647, -74.2878449820923], "neighborhood": [], "name": ["Mara\u2019s Continental Cuisine"], "starRating": ["4.5 star rating"], "phone": ["(732) 525-0045"], "priceRange": ["$$"], "address": ["3602 Rt 35 N", "South Amboy, NJ 08879"], "numberOfReviews": ["6 reviews"]},
{"category": ["Pizza"], "geoLocation": [40.4782214, -74.2823387], "neighborhood": [], "name": ["South Amboy Pizza Palace"], "starRating": ["4.5 star rating"], "phone": ["(732) 525-2474"], "priceRange": ["$$"], "address": ["346 Bordentown Ave", "South Amboy, NJ 08879"], "numberOfReviews": ["13 reviews"]},
{"category": ["Portuguese"], "geoLocation": [40.4651198, -74.264445], "neighborhood": [], "name": ["Fernandes Steakhouse 3"], "starRating": ["3.5 star rating"], "phone": ["(732) 721-2306"], "priceRange": ["$$"], "address": ["1776 Rt 35 N", "South Amboy, NJ 08879"], "numberOfReviews": ["17 reviews"]},
{"category": ["Pizza", "Italian", "Sports Bars"], "geoLocation": [40.4820125, -74.2791098], "neighborhood": [], "name": ["Sciortino\u2019s Harbor Lights"], "starRating": ["4.0 star rating"], "phone": ["(732) 721-8788"], "priceRange": ["$$"], "address": ["132 S Broadway", "South Amboy, NJ 08879"], "numberOfReviews": ["56 reviews"]},
{"category": ["Pizza"], "geoLocation": [40.4844303, -74.2856064], "neighborhood": [], "name": ["Don Giovanni \u00a0Wood Fired Pizza & Bar"], "starRating": ["3.0 star rating"], "phone": ["(732) 727-0733"], "priceRange": ["$$"], "address": ["276 Main St", "South Amboy, NJ 08879"], "numberOfReviews": ["15 reviews"]},
{"category": ["Portuguese"], "geoLocation": [40.466987, -74.2809385], "neighborhood": [], "name": ["Costa Verde"], "starRating": ["3.0 star rating"], "phone": ["(732) 727-7070"], "priceRange": ["$"], "address": ["6039 US Hwy 35", "South Amboy, NJ 08879"], "numberOfReviews": ["7 reviews"]},
{"category": ["Burgers"], "geoLocation": [40.4826009, -74.2795076], "neighborhood": [], "name": ["Big E\u2019s Burger Joint"], "starRating": ["4.0 star rating"], "phone": ["(732) 753-9933"], "priceRange": ["$$"], "address": ["115 S Broadway St", "South Amboy, NJ 08879"], "numberOfReviews": ["14 reviews"]},
{"category": ["Japanese"], "geoLocation": [40.4837761, -74.2804689], "neighborhood": [], "name": ["Hibachi Express & Sushi"], "starRating": ["4.5 star rating"], "phone": ["(732) 727-4888"], "priceRange": ["$"], "address": ["110 S Broadway", "South Amboy, NJ 08879"], "numberOfReviews": ["5 reviews"]},
{"category": ["American (Traditional)"], "geoLocation": [40.4852593, -74.2818512], "neighborhood": [], "name": ["Oriental House"], "starRating": ["4.0 star rating"], "phone": ["(732) 727-8981"], "priceRange": ["$"], "address": ["161 N Broadway", "South Amboy, NJ 08879"], "numberOfReviews": ["5 reviews"]},
{"category": ["Seafood"], "geoLocation": [40.464606, -74.2686115], "neighborhood": [], "name": ["Fishery"], "starRating": ["2.5 star rating"], "phone": ["(732) 721-9100"], "priceRange": ["$$"], "address": ["State Hwy 35", "South Amboy, NJ 08879"], "numberOfReviews": ["4 reviews"]},
{"category": ["Pizza", "Sandwiches"], "geoLocation": [40.484365, -74.2809128], "neighborhood": [], "name": ["Delio\u2019s Pizza & Hero Shop"], "starRating": ["4.5 star rating"], "phone": ["(732) 721-9440"], "priceRange": ["$"], "address": ["120 N Broadway", "South Amboy, NJ 08879"], "numberOfReviews": ["13 reviews"]},
{"category": ["American (New)", "Pubs"], "geoLocation": [40.4832948, -74.2800918], "neighborhood": [], "name": ["Blue Moon"], "starRating": ["4.0 star rating"], "phone": ["(732) 525-0014"], "priceRange": ["$$"], "address": ["114 S Broadway", "South Amboy, NJ 08879"], "numberOfReviews": ["9 reviews"]},
{"category": ["Diners", "American (Traditional)"], "geoLocation": [40.4845136, -74.2810185], "neighborhood": [], "name": ["Broadway Bistro"], "starRating": ["5.0 star rating"], "phone": ["(732) 721-9608"], "priceRange": [], "address": ["126 N Broadway St", "South Amboy, NJ 08879"], "numberOfReviews": ["1 review"]},
{"category": ["Seafood"], "geoLocation": [40.4840911, -74.2806653], "neighborhood": [], "name": ["Broadway Seafood"], "starRating": ["5.0 star rating"], "phone": ["(732) 721-0077"], "priceRange": [], "address": ["109 N Broadway", "South Amboy, NJ 08879"], "numberOfReviews": ["1 review"]},
{"category": ["Restaurants"], "geoLocation": [40.4820186, -74.2791004], "neighborhood": [], "name": ["Harbor Lights Inc"], "starRating": ["4.0 star rating"], "phone": ["(732) 721-8191"], "priceRange": ["$$"], "address": ["132 S Broadway", "South Amboy, NJ 08879"], "numberOfReviews": ["1 review"]},
{"category": ["Gas & Service Stations", "Fast Food"], "geoLocation": [40.4664881738984, -74.2891546765091], "neighborhood": [], "name": ["Cheesequake Travel Plaza"], "starRating": ["3.5 star rating"], "phone": ["(732) 525-0306"], "priceRange": ["$$"], "address": ["Garden State Pkwy", "South Amboy, NJ 08879"], "numberOfReviews": ["18 reviews"]},
{"category": ["Southern", "Soul Food"], "geoLocation": [40.4719795077072, -74.285409450531], "neighborhood": [], "name": ["Ms. Lee\u2019s Cuisine"], "starRating": ["3.0 star rating"], "phone": ["(732) 952-3600"], "priceRange": ["$"], "address": ["2087 Hwy 35", "South Amboy, NJ 08879"], "numberOfReviews": ["1 review"]},
{"category": ["Fast Food"], "geoLocation": [40.484308, -74.28014], "neighborhood": [], "name": ["Burger King"], "starRating": ["1.5 star rating"], "phone": ["(732) 525-0308"], "priceRange": [], "address": ["Garden State Pkwy", "South Amboy, NJ 08879"], "numberOfReviews": ["3 reviews"]},
{"category": ["American (New)", "Italian", "Diners"], "geoLocation": [40.464271615536, -74.2672080085183], "neighborhood": [], "name": ["Ocean Bay Diner"], "starRating": ["4.0 star rating"], "phone": ["(732) 313-7979"], "priceRange": ["$$"], "address": ["1803 Rt 35 S", "South Amboy, NJ 08879"], "numberOfReviews": ["3 reviews"]},
{"category": ["Delis", "Sandwiches"], "geoLocation": [40.4792762, -74.2850193], "neighborhood": [], "name": ["Colleen\u2019s Kitchen"], "starRating": [], "phone": ["(732) 525-9262"], "priceRange": [], "address": ["132 S Pine Ave", "South Amboy, NJ 08879"], "numberOfReviews": []}]